kybra/__init__.py
kybra/__main__.py
kybra/build_wasm_binary_or_exit.py
kybra/cargotoml.py
kybra/colors.py
kybra/module_bundler.py
kybra/py.typed
kybra/run_kybra_generate_or_exit.py
kybra/timed.py
kybra/types.py
kybra/canisters/__init__.py
kybra/canisters/ledger/NOTICE
kybra/canisters/ledger/__init__.py
kybra/canisters/management/__init__.py
kybra/canisters/management/basic.py
kybra/canisters/management/bitcoin.py
kybra/canisters/management/http.py
kybra/canisters/management/tecdsa.py
kybra/compiler/LICENSE-RustPython
kybra/compiler/__init__.py
kybra/compiler/install_rust_dependencies.sh
kybra/compiler/python_3_10_13_licenses.pdf
kybra/compiler/__pycache__/__init__.cpython-310.pyc
kybra/compiler/custom_modules/__init__.py
kybra/compiler/custom_modules/principal.py
kybra/compiler/custom_modules/__pycache__/__init__.cpython-310.pyc
kybra/compiler/custom_modules/__pycache__/principal.cpython-310.pyc
kybra/compiler/dfx_extension/extension.json
kybra/compiler/dfx_extension/install.sh
kybra/compiler/kybra_compile_python_stdlib/Cargo.toml
kybra/compiler/kybra_compile_python_stdlib/src/main.rs
kybra/compiler/kybra_generate/Cargo.toml
kybra/compiler/kybra_generate/src/constants.rs
kybra/compiler/kybra_generate/src/exit_codes.rs
kybra/compiler/kybra_generate/src/get_child_class_of.rs
kybra/compiler/kybra_generate/src/get_name.rs
kybra/compiler/kybra_generate/src/get_subscript_slice.rs
kybra/compiler/kybra_generate/src/keywords.rs
kybra/compiler/kybra_generate/src/lib.rs
kybra/compiler/kybra_generate/src/main.rs
kybra/compiler/kybra_generate/src/tuple.rs
kybra/compiler/kybra_generate/src/body/async_result_handler.rs
kybra/compiler/kybra_generate/src/body/call_global_python_function.rs
kybra/compiler/kybra_generate/src/body/guard_against_non_controllers.rs
kybra/compiler/kybra_generate/src/body/mod.rs
kybra/compiler/kybra_generate/src/body/unwrap_rust_python_result.rs
kybra/compiler/kybra_generate/src/body/utils.rs
kybra/compiler/kybra_generate/src/candid_type/array.rs
kybra-0.7.1.dist-info/licenses/LICENSE
kybra-0.7.1.dist-info/licenses/NOTICE
kybra-0.7.1.dist-info/licenses/NOTICE_PYTHON
kybra-0.7.1.dist-info/METADATA
kybra-0.7.1.dist-info/WHEEL
kybra-0.7.1.dist-info/top_level.txt
kybra-0.7.1.dist-info/RECORD
