Metadata-Version: 2.4
Name: kybra
Version: 0.7.1
License-File: LICENSE
License-File: NOTICE
License-File: NOTICE_PYTHON
Requires-Dist: modulegraph==0.19.3
Dynamic: description
Dynamic: description-content-type
Dynamic: license-file
Dynamic: requires-dist
